chimpy_me/__init__.py
chimpy_me-0.0.1a1.dist-info/METADATA
chimpy_me-0.0.1a1.dist-info/WHEEL
chimpy_me-0.0.1a1.dist-info/licenses/LICENSE
chimpy_me-0.0.1a1.dist-info/RECORD
