Metadata-Version: 2.4
Name: chimpy-me
Version: 0.0.1a1
Summary: Library bot framework with traditional modules and MCP services for institutions
Project-URL: Homepage, https://github.com/chimpy-me/chimpy-me
Project-URL: Repository, https://github.com/chimpy-me/chimpy-me
Project-URL: Issues, https://github.com/chimpy-me/chimpy-me/issues
Author: Ray Voelker
License-Expression: MIT
License-File: LICENSE
Classifier: Development Status :: 2 - Pre-Alpha
Classifier: License :: OSI Approved :: MIT License
Classifier: Programming Language :: Python :: 3
Requires-Python: >=3.14
Provides-Extra: dev
Requires-Dist: pytest>=8.0; extra == 'dev'
Requires-Dist: ruff>=0.4; extra == 'dev'
